<?xml version="1.0" encoding="UTF-8"?>
<!DOCTYPE suite SYSTEM "https://testng.org/testng-1.0.dtd">


<suite name="TestParameter">
  <test thread-count="1" name="TestParameter">
  
  
  <parameter name="browser" value="chrome"></parameter>
 <parameter name="username" value="adityaverma@gmail.com"></parameter>
 <parameter name="password" value="123456"></parameter>
  <classes>
  
  <class name="Sample1.TestParameter"></class>
 
  </classes>
 
  
  </test> <!-- Test -->
</suite> <!-- Suite -->
